odoo/addons/web_select_all_companies/README.rst
odoo/addons/web_select_all_companies/__init__.py
odoo/addons/web_select_all_companies/__manifest__.py
odoo/addons/web_select_all_companies/i18n/es.po
odoo/addons/web_select_all_companies/i18n/fr.po
odoo/addons/web_select_all_companies/i18n/it.po
odoo/addons/web_select_all_companies/i18n/web_select_all_companies.pot
odoo/addons/web_select_all_companies/readme/CONTRIBUTORS.rst
odoo/addons/web_select_all_companies/readme/DESCRIPTION.rst
odoo/addons/web_select_all_companies/static/description/icon.png
odoo/addons/web_select_all_companies/static/description/index.html
odoo/addons/web_select_all_companies/static/description/select_all_companies.gif
odoo/addons/web_select_all_companies/static/src/js/switch_all_company_menu.esm.js
odoo/addons/web_select_all_companies/static/src/scss/switch_all_company_menu.scss
odoo/addons/web_select_all_companies/static/src/xml/switch_all_company_menu.xml
odoo_addon_web_select_all_companies-16.0.1.0.1.6.dist-info/METADATA
odoo_addon_web_select_all_companies-16.0.1.0.1.6.dist-info/WHEEL
odoo_addon_web_select_all_companies-16.0.1.0.1.6.dist-info/top_level.txt
odoo_addon_web_select_all_companies-16.0.1.0.1.6.dist-info/RECORD
